CHANGES.txt
LICENSE.txt
MANIFEST.in
README.txt
botnee_profile.txt
ms.txt
pip-log.txt
setup.py
sfood.txt
botnee/__init__.py
botnee/__main__.py
botnee/counter.py
botnee/debug.py
botnee/doc_manager_store.py
botnee/doc_store.py
botnee/engine.py
botnee/errors.py
botnee/filters.py
botnee/get_related.py
botnee/json_io.py
botnee/json_token_parser.py
botnee/persistent_dict.py
botnee/rss_writer.py
botnee/standard_document.py
botnee/standard_document_io.py
botnee/test_harness.py
botnee/timeout_lock.py
botnee/timer.py
botnee.egg-info/.MySCMServerInfo
botnee.egg-info/PKG-INFO
botnee.egg-info/SOURCES.txt
botnee.egg-info/dependency_links.txt
botnee.egg-info/requires.txt
botnee.egg-info/top_level.txt
botnee/helpers/__init__.py
botnee/helpers/marshal_to_json.py
botnee/process/__init__.py
botnee/process/data_dict.py
botnee/process/matrix_dict.py
botnee/process/meta_dict.py
botnee/process/text.py
botnee/process/time_dict.py
botnee/process/topic_model.py
botnee/process/vector_space_model.py
botnee/taxonomy/__init__.py
botnee/taxonomy/metamap_tagger.py
botnee/taxonomy/metamap_wrapper.py
botnee/test/__init__.py
botnee/test/test_corpus.py
botnee/test/test_files.py
botnee/test/test_filter_results.py
botnee/test/test_get_related.py
botnee/test/test_json_io.py
botnee/test/test_process.py
botnee/test/test_search.py
botnee/test/test_standard_document_io.py
botnee/web/__init__.py
botnee/web/manage.py
botnee/web/settings.py
botnee/web/urls.py
botnee/web/interface/__init__.py
botnee/web/interface/models.py
botnee/web/interface/tests.py
botnee/web/interface/views.py