Metadata-Version: 1.0
Name: botnee
Version: 0.1.2e
Summary: The botnee tool.
Home-page: http://pypi.python.org/pypi/botnee/
Author: T. Diethe
Author-email: tdiethe@bmjgroup.com
License: LICENSE.txt
Platform: UNKNOWN
